setup.py
gandb_probability/Binomialdistribution.py
gandb_probability/Gaussiandistribution.py
gandb_probability/Generaldistribution.py
gandb_probability/__init__.py
gandb_probability.egg-info/PKG-INFO
gandb_probability.egg-info/SOURCES.txt
gandb_probability.egg-info/dependency_links.txt
gandb_probability.egg-info/not-zip-safe
gandb_probability.egg-info/top_level.txt