Metadata-Version: 1.0
Name: gandb-probability
Version: 0.1.0
Summary: Gaussian and Binomial distributions
Home-page: UNKNOWN
Author: Mark Awuku
Author-email: awukum18@gmail.com
License: UNKNOWN
Platform: UNKNOWN
